simply_progress/__init__.py
simply_progress/progress.py
simply_progress-0.0.1.dist-info/LICENSE.txt
simply_progress-0.0.1.dist-info/METADATA
simply_progress-0.0.1.dist-info/WHEEL
simply_progress-0.0.1.dist-info/top_level.txt
simply_progress-0.0.1.dist-info/RECORD
